asn1editor/ASN1SpecHandler.py
asn1editor/Plugin.py
asn1editor/PluginInterface.py
asn1editor/TypeAugmenter.py
asn1editor/ViewControllerFactory.py
asn1editor/__init__.py
asn1editor/controller/ChoiceInstanceFactory.py
asn1editor/controller/Controller.py
asn1editor/controller/ControllerFactory.py
asn1editor/controller/Converter.py
asn1editor/controller/ListInstanceFactory.py
asn1editor/controller/__init__.py
asn1editor/interfaces/BitstringInterface.py
asn1editor/interfaces/OptionalInterface.py
asn1editor/interfaces/ValueInterface.py
asn1editor/interfaces/__init__.py
asn1editor/view/AbstractView.py
asn1editor/view/AbstractViewFactory.py
asn1editor/view/__init__.py
asn1editor/wxPython/Environment.py
asn1editor/wxPython/FilePickerHandler.py
asn1editor/wxPython/ImageList.py
asn1editor/wxPython/Labels.py
asn1editor/wxPython/MainWindow.py
asn1editor/wxPython/MenuHandler.py
asn1editor/wxPython/Resources.py
asn1editor/wxPython/SingleFileDropTarget.py
asn1editor/wxPython/TreeView.py
asn1editor/wxPython/ViewSelect.py
asn1editor/wxPython/WxPythonViewFactory.py
asn1editor/wxPython/__init__.py
asn1editor/wxPython/icons/bitstring.svg
asn1editor/wxPython/icons/bool.svg
asn1editor/wxPython/icons/choice.svg
asn1editor/wxPython/icons/date.svg
asn1editor/wxPython/icons/enumerated.svg
asn1editor/wxPython/icons/exit.svg
asn1editor/wxPython/icons/float.svg
asn1editor/wxPython/icons/integer.svg
asn1editor/wxPython/icons/load_encoded.svg
asn1editor/wxPython/icons/open.svg
asn1editor/wxPython/icons/recent.svg
asn1editor/wxPython/icons/root.svg
asn1editor/wxPython/icons/save_encoded.svg
asn1editor/wxPython/icons/sequence.svg
asn1editor/wxPython/icons/sequence_of.svg
asn1editor/wxPython/icons/string.svg
asn1editor/wxPython/icons/time.svg
asn1editor/wxPython/views/WxPythonBitstringView.py
asn1editor/wxPython/views/WxPythonBooleanView.py
asn1editor/wxPython/views/WxPythonChoiceView.py
asn1editor/wxPython/views/WxPythonContainerView.py
asn1editor/wxPython/views/WxPythonDateTimeViews.py
asn1editor-0.8.0.dist-info/LICENSE
asn1editor-0.8.0.dist-info/METADATA
asn1editor-0.8.0.dist-info/WHEEL
asn1editor-0.8.0.dist-info/entry_points.txt
asn1editor-0.8.0.dist-info/top_level.txt
asn1editor-0.8.0.dist-info/RECORD
