Metadata-Version: 2.1
Name: asn1editor
Version: 0.8.0
Summary: ASN.1 editor framework with support for encoding and decoding various codecs.
Home-page: https://github.com/futsch1/asn1editor
Author: Florian Fetz
Author-email: florian.fetz@gmail.com
License: MIT
Keywords: ASN.1,asn1,editor
Classifier: License :: OSI Approved :: MIT License
Classifier: Programming Language :: Python :: 3
Classifier: Topic :: Software Development
Requires-Python: >=3.6
License-File: LICENSE
Requires-Dist: asn1tools >=0.153.0
Requires-Dist: wxpython >=4.1.0
